etcd3/__init__.py
etcd3/aio_client.py
etcd3/baseclient.py
etcd3/client.py
etcd3/models.py
etcd3/swagger_helper.py
etcd3/utils.py
etcd3/version.py
etcd3/apis/__init__.py
etcd3/apis/auth.py
etcd3/apis/base.py
etcd3/apis/cluster.py
etcd3/apis/extra.py
etcd3/apis/kv.py
etcd3/apis/lease.py
etcd3/apis/lock.py
etcd3/apis/maintenance.py
etcd3/apis/watch.py
etcd3/contrib/__init__.py
etcd3/errors/__init__.py
etcd3/errors/errors.py
etcd3/errors/go_etcd_rpctypes_error.py
etcd3/errors/go_grpc_codes.py
etcd3/errors/go_grpc_gateway_errors.py
etcd3/errors/go_net_http_status.py
etcd3/stateful/__init__.py
etcd3/stateful/lease.py
etcd3/stateful/lock.py
etcd3/stateful/transaction.py
etcd3/stateful/watch.py
etcd3/swaggerdefs/README.md
etcd3/swaggerdefs/__init__.py
etcd3/swaggerdefs/v3_2_x/__init__.py
etcd3/swaggerdefs/v3_2_x/rpc.swagger.json
etcd3/swaggerdefs/v3_2_x/v3election.swagger.json
etcd3/swaggerdefs/v3_2_x/v3lock.swagger.json
etcd3/swaggerdefs/v3_3_x/__init__.py
etcd3/swaggerdefs/v3_3_x/rpc.swagger.json
etcd3/swaggerdefs/v3_3_x/v3election.swagger.json
etcd3/swaggerdefs/v3_3_x/v3lock.swagger.json
etcd3_py-0.1.6.dist-info/LICENSE
etcd3_py-0.1.6.dist-info/METADATA
etcd3_py-0.1.6.dist-info/WHEEL
etcd3_py-0.1.6.dist-info/top_level.txt
etcd3_py-0.1.6.dist-info/RECORD
