Metadata-Version: 2.1
Name: etcd3-py
Version: 0.1.6
Summary: Python client for etcd v3 (Using gRPC-JSON-Gateway)
Home-page: https://github.com/revolution1/etcd3-py
Author: Renjie Cai
Author-email: revol.cai@gmail.com
License: Apache Software License 2.0
Keywords: etcd3
Platform: UNKNOWN
Classifier: Development Status :: 4 - Beta
Classifier: Intended Audience :: Developers
Classifier: License :: OSI Approved :: Apache Software License
Classifier: Natural Language :: English
Classifier: Programming Language :: Python :: 2.7
Classifier: Programming Language :: Python :: 3.5
Classifier: Programming Language :: Python :: 3.6
Classifier: Programming Language :: Python :: 3.7
Requires-Python: >=2.7, !=3.0.*, !=3.1.*, !=3.2.*, !=3.3.*, !=3.4.*
